nvwa/__init__.py
nvwa/jiajia.py
nvwa/nvwa.py
nvwa-0.1b1.dist-info/LICENSE
nvwa-0.1b1.dist-info/METADATA
nvwa-0.1b1.dist-info/WHEEL
nvwa-0.1b1.dist-info/top_level.txt
nvwa-0.1b1.dist-info/RECORD
