Metadata-Version: 2.1
Name: nvwa
Version: 0.1b1
Summary: A personal project
Home-page: https://github.com/jajupmochi/Nvwa
Author: Linlin Jia
Author-email: linlin.jia@insa-rouen.fr
License: UNKNOWN
Platform: UNKNOWN
Classifier: Programming Language :: Python :: 3
Classifier: License :: OSI Approved :: GNU General Public License v3 (GPLv3)
Classifier: Operating System :: OS Independent
Requires-Dist: networkx (>=2.2)
